{
  "text": [
    {
      "attributes": {
        "show": "0:21"
      },
      "text": "Supremo Criador,\ndo bem \u00e9s manancial.\nCom Tua gra\u00e7a e Teu amor\nlivraste-me do mal.\nCom Tua gra\u00e7a e Teu amor\nlivraste-me do mal."
    },
    {
      "attributes": {
        "show": "0:55"
      },
      "text": "Feitura Tua sou,\nde Ti a vida vem.\nO Teu maravilhoso amor\nme ampara e me sust\u00e9m;\nO Teu maravilhoso amor\nme ampara e me sust\u00e9m."
    },
    {
      "attributes": {
        "show": "1:28"
      },
      "text": "Que sempre Teu poder\nimpere, \u00f3 Deus, aqui;\nE faz-me sempre ser fiel\nme unindo, \u00f3 Deus, a Ti.\nE faz-me sempre ser fiel\nme unindo, \u00f3 Deus, a Ti."
    }
  ],
  "attributes": {
    "number": "005",
    "title": "Supremo Criador",
    "author": "Anne Steele  |  HYMNS AND TUNES",
    "verse": "Salmo 105:1-3",
    "music": "005.mp3",
    "offset": "0:00"
  }
}
