{
  "text": [
    {
      "attributes": {
        "show": "0:26"
      },
      "text": "O c\u00e9u azul na amplid\u00e3o,\nEstrelas mil em multid\u00e3o,\nA luz do c\u00e9u e seu fulgor\nProclamar\u00e3o o Criador."
    },
    {
      "attributes": {
        "show": "0:54"
      },
      "text": "O Sol de luz, com seu calor,\nLouvor dar\u00e1 ao seu Autor,\nE sem falar, a resplender,\nDir\u00e1 de Deus e Seu poder."
    },
    {
      "attributes": {
        "show": "1:23"
      },
      "text": "Ao grande Deus,\no som do mar,\nA flor gentil, a voz do ar,\nA doce paz da noite azul\nAclamar\u00e3o de norte a sul."
    },
    {
      "attributes": {
        "show": "1:50"
      },
      "text": "Assim dir\u00e3o o c\u00e9u e o mar,\nDo Seu poder e amor sem-par.\nE v\u00f3s, na\u00e7\u00f5es, clamai tamb\u00e9m!\nLouvai a Deus, Senhor! Am\u00e9m."
    }
  ],
  "attributes": {
    "title": "O C\u00e9u Azul",
    "author": "Joseph Addison | Franz Joseph Haydn",
    "verse": "Salmo 19:1-4"
  }
}
