{
  "text": [
    "Conta-me a velha hist\u00f3ria,\nsuave, com dul\u00e7or,\nDe meu Jesus e Sua gl\u00f3ria,\nde Cristo e Seu amor,",
    "Com calma e com paci\u00eancia,\npois quero alcan\u00e7ar\nA altura do mist\u00e9rio:\nque Deus nos pode amar.",
    "Conta-me a velha hist\u00f3ria,\nVelha e sublime hist\u00f3ria!\nConta-me, pois, a hist\u00f3ria\nDo meigo Salvador!",
    "Fala-me com do\u00e7ura\ndo meigo Redentor,\nDe Seu amor e Sua gra\u00e7a,\npois sou um pecador;",
    "Sim, para o meu conforto,\nem tempos de afli\u00e7\u00e3o,\nRepete a velha hist\u00f3ria\nde amor e salva\u00e7\u00e3o.",
    "Conta-me a velha hist\u00f3ria,\nVelha e sublime hist\u00f3ria!\nConta-me, pois, a hist\u00f3ria\nDo meigo Salvador!",
    "Se o brilho deste mundo\ntoldar do C\u00e9u a luz,\nRepete ent\u00e3o a mesma hist\u00f3ria\nda gra\u00e7a de Jesus!",
    "E quando, enfim, a gl\u00f3ria\ndo mundo al\u00e9m raiar,\nOh, conta a mesma hist\u00f3ria:\nque veio aqui salvar.",
    "Conta-me a velha hist\u00f3ria,\nVelha e sublime hist\u00f3ria!\nConta-me, pois, a hist\u00f3ria\nDo meigo Salvador!"
  ],
  "attributes": {
    "title": "Conta-me a Velha Hist\u00f3ria",
    "author": "Arabella Katherine Hankey | William Howard Doane",
    "verse": "Jo\u00e3o 3:16"
  }
}
