{
  "text": [
    "Ao ver a cruz,\nmeu rude cora\u00e7\u00e3o\nFica em sil\u00eancio\nante tanto horror!",
    "Penso nos pregos\nsobre Suas m\u00e3os,\nE como a s\u00f3s\nmorreu por ter-me amor!",
    "Vejo o Calv\u00e1rio,\no monte t\u00e3o cruel!\nAli, Jesus,\npregado foi na cruz.",
    "Vejo o Calv\u00e1rio,\no monte do amor!\nA minha culpa\nali Jesus pagou.",
    "Aos olhos v\u00eam\nas cenas t\u00e3o cru\u00e9is,\nE humildemente\neu penso em Seu amor.",
    "Ent\u00e3o minh\u2019alma\nem muda contri\u00e7\u00e3o,\nEterna gra\u00e7a\nrende ao Salvador.",
    "Vejo o Calv\u00e1rio,\no monte t\u00e3o cruel!\nAli, Jesus,\npregado foi na cruz.",
    "Vejo o Calv\u00e1rio,\no monte do amor!\nA minha culpa\nali Jesus pagou.",
    "Ao meditar\nnas dores que sofreu,\nEu sinto mais\namor por meu Jesus.",
    "Se foi ali\nque Seu perd\u00e3o me deu,\nFeliz eu sou,\ne grato ao ver a cruz.",
    "Vejo o Calv\u00e1rio,\no monte t\u00e3o cruel!\nAli, Jesus,\npregado foi na cruz.",
    "Vejo o Calv\u00e1rio,\no monte do amor!\nA minha culpa\nali Jesus pagou."
  ],
  "attributes": {
    "title": "Ao Ver a Cruz",
    "author": "C. H. L. | Carl Harold Lowden",
    "verse": "Lucas 23:33-38"
  }
}
