{
  "text": [
    {
      "attributes": {
        "show": "0:17",
        "image": "HASD-152A.jpg"
      },
      "text": "J\u00e1 refulge a gl\u00f3ria eterna\nde Jesus, o Rei dos reis;\nBreve os reinos deste mundo\nouvir\u00e3o as Suas leis!"
    },
    {
      "attributes": {
        "show": "0:31",
        "image": "HASD-152A.jpg"
      },
      "text": "Os sinais da Sua vinda\nmais se mostram cada vez.\nVencendo vem Jesus!"
    },
    {
      "attributes": {
        "show": "0:43",
        "image": "HASD-152B.jpg",
        "italic": "true"
      },
      "text": "Gl\u00f3ria, gl\u00f3ria! Aleluia!\nGl\u00f3ria, gl\u00f3ria! Aleluia!\nGl\u00f3ria, gl\u00f3ria! Aleluia!\nVencendo vem Jesus!"
    },
    {
      "attributes": {
        "show": "1:04",
        "image": "HASD-152A.jpg"
      },
      "text": "O clarim que chama\nos crentes\n\u00e0 batalha j\u00e1 soou;\nCristo \u00e0 frente do Seu povo,\nmultid\u00f5es j\u00e1 conquistou."
    },
    {
      "attributes": {
        "show": "1:15",
        "image": "HASD-152A.jpg"
      },
      "text": "O inimigo em retirada,\nSeu furor patenteou.\nVencendo vem Jesus!"
    },
    {
      "attributes": {
        "show": "1:26",
        "image": "HASD-152B.jpg",
        "italic": "true"
      },
      "text": "Gl\u00f3ria, gl\u00f3ria! Aleluia!\nGl\u00f3ria, gl\u00f3ria! Aleluia!\nGl\u00f3ria, gl\u00f3ria! Aleluia!\nVencendo vem Jesus!"
    },
    {
      "attributes": {
        "show": "1:48",
        "image": "HASD-152A.jpg"
      },
      "text": "E por fim, entronizado,\nas na\u00e7\u00f5es h\u00e1 de julgar;\nTodos, grandes e pequenos,\no Juiz h\u00e3o de encarar."
    },
    {
      "attributes": {
        "show": "1:58",
        "image": "HASD-152A.jpg"
      },
      "text": "E os remidos, triunfantes,\nem fulgor h\u00e3o de cantar:\nVencido tem Jesus!"
    },
    {
      "attributes": {
        "show": "2:10",
        "image": "HASD-152B.jpg",
        "italic": "true"
      },
      "text": "Gl\u00f3ria, gl\u00f3ria! Aleluia!\nGl\u00f3ria, gl\u00f3ria! Aleluia!\nGl\u00f3ria, gl\u00f3ria! Aleluia!\nVencido tem Jesus!"
    }
  ],
  "attributes": {
    "number": "152",
    "image": "HASD-152A.jpg",
    "title": "Vencendo Vem Jesus",
    "author": "Julia Ward Howe | Melodia Tradicional Americana",
    "verse": "Apocalipse 11:15",
    "music": "152.mp3",
    "offset": "0:00"
  }
}
