{
  "text": [
    {
      "attributes": {
        "show": "0:19"
      },
      "text": "Quem ouvir as novas,\nv\u00e1 proclamar:\nSalva\u00e7\u00e3o de gra\u00e7a,\nvinde desfrutar!"
    },
    {
      "attributes": {
        "show": "0:29"
      },
      "text": "Oh! que o mundo inteiro\nou\u00e7a anunciar:\nTodo que quiser \u00e9 vir!"
    },
    {
      "attributes": {
        "show": "0:39"
      },
      "text": "Todo que quiser,\nvenha receber!\nPossam todos\nessa boa nova ouvir."
    },
    {
      "attributes": {
        "show": "0:49"
      },
      "text": "\u00c9 o Pai celeste\nquem convida assim:\nTodo que quiser \u00e9 vir!"
    },
    {
      "attributes": {
        "show": "1:00"
      },
      "text": "Quem quiser agora,\nvenha aceitar;\nEis a porta aberta,\nj\u00e1 podeis entrar;"
    },
    {
      "attributes": {
        "show": "1:10"
      },
      "text": "\u00c9 Jesus caminho\npara ao C\u00e9u chegar;\nTodo que quiser \u00e9 vir!"
    },
    {
      "attributes": {
        "show": "1:20"
      },
      "text": "Todo que quiser,\nvenha receber!\nPossam todos\nessa boa nova ouvir."
    },
    {
      "attributes": {
        "show": "1:30"
      },
      "text": "\u00c9 o Pai celeste\nquem convida assim:\nTodo que quiser \u00e9 vir!"
    },
    {
      "attributes": {
        "show": "1:41"
      },
      "text": "Que fiel promessa\ntens, pecador!\nQueres ter a vida?\nVem ao Salvador!"
    },
    {
      "attributes": {
        "show": "1:51"
      },
      "text": "Ele a todos fala\ncom mui terno amor:\nTodo que quiser \u00e9 vir!"
    },
    {
      "attributes": {
        "show": "2:01"
      },
      "text": "Todo que quiser,\nvenha receber!\nPossam todos\nessa boa nova ouvir."
    },
    {
      "attributes": {
        "show": "2:11"
      },
      "text": "\u00c9 o Pai celeste\nquem convida assim:\nTodo que quiser \u00e9 vir!"
    }
  ],
  "attributes": {
    "title": "Quem Ouvir as Novas",
    "author": "P. P. B. | Philip Paul Bliss",
    "verse": "Isa\u00edas 40:9"
  }
}
