{
  "text": [
    "Ouvi Jesus a me dizer:\n\u201c\u00d3 vem, descansa em Mim;\nE no Meu seio podes ter\nconsola\u00e7\u00e3o sem fim.\u201d",
    "Ent\u00e3o eu vim e Lhe entreguei\nmeu triste cora\u00e7\u00e3o.\nAbrigo, paz, conforto achei;\nem Cristo achei perd\u00e3o.",
    "Ouvi Jesus a me dizer:\n\u201cDa \u00e1gua viva Eu dou;\n\u00d3 vem, de gra\u00e7a vem beber,\npois Eu a fonte sou.\u201d",
    "Eu vim a Cristo e me prostrei\n\u00e0s \u00e1guas e bebi;\nJamais a sede sentirei,\nestando eu sempre aqui.",
    "Ouvi Jesus a me dizer:\n\u201cA luz do mundo Eu sou.\n\u00d3 vem a Mim! A quem vier,\na luz da vida Eu dou.\u201d",
    "A Ele eu vim e nEle achei\no Sol que brilha em mim.\nE nessa luz eu sempre irei,\nat\u00e9 da vida o fim."
  ],
  "attributes": {
    "title": "Ouvi Jesus a me Dizer",
    "author": "Horatius Bonar | Louis Spohr",
    "verse": "Mateus 11:28-30"
  }
}
