{
  "text": [
    {
      "attributes": {
        "show": "0:20"
      },
      "text": "Cantarei de Jesus Cristo,\nQue na cruz por mim morreu;\nO desprezo suportando,\nSalva\u00e7\u00e3o me concedeu."
    },
    {
      "attributes": {
        "show": "0:40",
        "italic": true
      },
      "text": "Cantarei que Jesus Cristo\nCom amor me resgatou!\nEle sobre a cruz foi morto;\nMeus pecados perdoou."
    },
    {
      "attributes": {
        "show": "1:00"
      },
      "text": "Cantarei de Jesus Cristo,\nSua gra\u00e7a exaltarei;\nEncontrou-me muito aflito,\nE descanso nEle achei."
    },
    {
      "attributes": {
        "show": "1:21",
        "italic": true
      },
      "text": "Cantarei que Jesus Cristo\nCom amor me resgatou!\nEle sobre a cruz foi morto;\nMeus pecados perdoou."
    },
    {
      "attributes": {
        "show": "1:41"
      },
      "text": "Cantarei de Jesus Cristo,\nE de como me encontrou,\nE do mundo e do pecado,\nCom amor me libertou."
    },
    {
      "attributes": {
        "show": "2:01",
        "italic": true
      },
      "text": "Cantarei que Jesus Cristo\nCom amor me resgatou!\nEle sobre a cruz foi morto;\nMeus pecados perdoou."
    },
    {
      "attributes": {
        "show": "2:22"
      },
      "text": "Cantarei no C\u00e9u, a Cristo,\nBendirei Seu grande amor;\nCom fervor, eternamente,\nAo meu Rei darei louvor."
    },
    {
      "attributes": {
        "show": "2:42",
        "italic": true
      },
      "text": "Cantarei que Jesus Cristo\nCom amor me resgatou!\nEle sobre a cruz foi morto;\nMeus pecados perdoou."
    }
  ],
  "attributes": {
    "title": "Cantarei de Jesus Cristo",
    "author": "Philip Paul Bliss | James McGranahan",
    "verse": "Jo\u00e3o 3:17"
  }
}
