{
  "text": [
    {
      "attributes": {
        "show": "0:19"
      },
      "text": "Em mim vem habitar,\n\u00f3 vem, Jesus,\nE em mim fazer brilhar\na Tua luz!"
    },
    {
      "attributes": {
        "show": "0:40"
      },
      "text": "Eis a minha ambi\u00e7\u00e3o:\nter e sentir, Senhor,\nMais gratid\u00e3o\ne mais amor."
    },
    {
      "attributes": {
        "show": "1:01"
      },
      "text": "Os passos Teus seguir\neu quero, sim,\nPra Te servir e amar\nat\u00e9 o fim."
    },
    {
      "attributes": {
        "show": "1:21"
      },
      "text": "Eis o meu desejar,\nmeu ideal maior:\nContigo andar,\n\u00f3 Salvador."
    },
    {
      "attributes": {
        "show": "1:42"
      },
      "text": "Em meu interior\nvem Tu brilhar.\nFaz-me, com mais ardor,\nda cruz falar."
    },
    {
      "attributes": {
        "show": "2:02"
      },
      "text": "Reveste o cora\u00e7\u00e3o\nde Teu excelso amor,\nDe retid\u00e3o e de fervor."
    },
    {
      "attributes": {
        "show": "2:23"
      },
      "text": "Oh! que consola\u00e7\u00e3o\na Cristo amar,\nPois que com tanto amor\nme quis salvar!"
    },
    {
      "attributes": {
        "show": "2:43"
      },
      "text": "Nada me alegra mais,\ngozo n\u00e3o h\u00e1 maior\nQue Tua paz, \u00f3 Salvador."
    }
  ],
  "attributes": {
    "number": "406",
    "title": "Em Mim Vem Habitar",
    "author": "Jo\u00e3o Corr\u00eaa da Costa | William Howard Doane",
    "verse": "Jo\u00e3o 14:23",
    "music": "406.mp3",
    "offset": "0:00"
  }
}
