{
  "text": [
    {
      "attributes": {
        "show": "0:21",
        "image": "HASD-519.jpg"
      },
      "text": "\u00d3 Tu que deste o p\u00e3o,\nl\u00e1 junto ao mar,\nVem d\u00e1-lo a mim tamb\u00e9m,\nJesus, vem dar!"
    },
    {
      "attributes": {
        "show": "0:44",
        "image": "HASD-519.jpg"
      },
      "text": "Pois, na Palavra, \u00f3 Deus,\np\u00e3o busco achar,\nO santo p\u00e3o que me h\u00e1\nde sustentar."
    },
    {
      "attributes": {
        "show": "1:07",
        "image": "HASD-519.jpg"
      },
      "text": "Vem Tua b\u00ean\u00e7\u00e3o dar,\nvem, \u00f3 Senhor;\nVem e revela, ent\u00e3o,\no Teu amor."
    },
    {
      "attributes": {
        "show": "1:29",
        "image": "HASD-519.jpg"
      },
      "text": "Pai, muitas gra\u00e7as dou\npor este p\u00e3o,\nLuz que prov\u00e9m do C\u00e9u\ne traz perd\u00e3o."
    },
    {
      "attributes": {
        "show": "1:52",
        "image": "HASD-519.jpg"
      },
      "text": "\u00c9 vida o Teu falar,\nsim, ao que crer.\nEu quero a lei guardar,\ne em Ti viver,"
    },
    {
      "attributes": {
        "show": "2:14",
        "image": "HASD-519.jpg"
      },
      "text": "Mas fraco sou, Senhor,\nvem me ajudar,\nSim, sempre at\u00e9 ao lar\nde al\u00e9m chegar."
    }
  ],
  "attributes": {
    "number": "519",
    "image": "HASD-519.jpg",
    "title": "O P\u00e3o da Vida",
    "author": "Mary Artemisia Lathbury | William Fisk Sherwin",
    "verse": "Jo\u00e3o 6:51",
    "music": "519.mp3",
    "offset": "0:00"
  }
}
