{
  "text": [
    "Vem o grande dia,\no grande dia,\nVem o grande dia,\nsem tardar,",
    "Quando os \u00edmpios e santos\nseparados h\u00e3o de ser;\n\u2018Stais v\u00f3s prontos\npara o dia final?",
    "\u2018Stais v\u00f3s prontos?\n\u2018Stais v\u00f3s prontos?\n\u2018Stais v\u00f3s prontos\npara o dia final?",
    "\u2018Stais v\u00f3s prontos?\n\u2018Stais v\u00f3s prontos\nPara o dia final?",
    "Vem o alegre dia,\no alegre dia,\nEste alegre dia\nperto est\u00e1,",
    "Mas alegre ser\u00e1 somente\nao que ama o Salvador;\n\u2018Stais v\u00f3s prontos\npara o dia final?",
    "\u2018Stais v\u00f3s prontos?\n\u2018Stais v\u00f3s prontos?\n\u2018Stais v\u00f3s prontos\npara o dia final?",
    "\u2018Stais v\u00f3s prontos?\n\u2018Stais v\u00f3s prontos\nPara o dia final?",
    "Um glorioso dia,\nglorioso dia,\nUm glorioso dia\nh\u00e1 de ser,",
    "Mas a gl\u00f3ria vir\u00e1 somente\nao que ama o Salvador;\n\u2018Stais v\u00f3s prontos\npara o dia final?",
    "\u2018Stais v\u00f3s prontos?\n\u2018Stais v\u00f3s prontos?\n\u2018Stais v\u00f3s prontos\npara o dia final?",
    "\u2018Stais v\u00f3s prontos?\n\u2018Stais v\u00f3s prontos\nPara o dia final?"
  ],
  "attributes": {
    "title": "Vem o Grande Dia",
    "author": "W. L. T. | Will Lamartine Thompson",
    "verse": "Sofonias 1:14"
  }
}
