{
  "text": [
    {
      "attributes": {
        "show": "0:43"
      },
      "text": "Em humilde ora\u00e7\u00e3o,\nQuero dedicar, Senhor,\nMeu indigno cora\u00e7\u00e3o,\nPara Teu louvor."
    },
    {
      "attributes": {
        "show": "1:05"
      },
      "text": "Faz-me puro, santo e bom\nPra cumprir o Teu querer.\nD\u00e1-me amor,\nTeu grande dom;\nD\u00e1-me Teu poder."
    }
  ],
  "attributes": {
    "number": "597",
    "title": "Humilde Ora\u00e7\u00e3o",
    "author": "A. R. e A. B. | Ademir Rodriguez e Amauri Barboza",
    "verse": "Salmo 51:10",
    "music": "597.mp3",
    "offset": "0:00"
  }
}
